aioscrapy/__init__.py
aioscrapy/cache.py
aioscrapy/client.py
aioscrapy/html.py
aioscrapy/session.py
aioscrapy/typedefs.py
aioscrapy/worker.py
aioscrapy-0.2.0.dist-info/LICENSE
aioscrapy-0.2.0.dist-info/METADATA
aioscrapy-0.2.0.dist-info/WHEEL
aioscrapy-0.2.0.dist-info/top_level.txt
aioscrapy-0.2.0.dist-info/RECORD
