Metadata-Version: 2.1
Name: aioscrapy
Version: 0.2.0
Summary: Python asynchronous library for web scraping
Home-page: https://github.com/eugen1j/aioscrapy
Author: eugen1j
Author-email: eugenij.bondar@gmail.com
License: MIT
Keywords: python3
Platform: UNKNOWN
Classifier: License :: OSI Approved :: MIT License
Classifier: Programming Language :: Python
Classifier: Programming Language :: Python :: 3.7
Classifier: Development Status :: 3 - Alpha
Classifier: Framework :: AsyncIO
Classifier: Operating System :: Unix
Classifier: Operating System :: Microsoft :: Windows
Classifier: Operating System :: MacOS
Requires-Python: >=3.7.0
Requires-Dist: aiohttp
